LICENSE
MANIFEST.in
README.md
setup.py
local_llama_index/VERSION
local_llama_index/__init__.py
local_llama_index/async_utils.py
local_llama_index/constants.py
local_llama_index/docstore.py
local_llama_index/img_utils.py
local_llama_index/old_docstore.py
local_llama_index/py.typed
local_llama_index/schema.py
local_llama_index/types.py
local_llama_index/utils.py
local_llama_index.egg-info/PKG-INFO
local_llama_index.egg-info/SOURCES.txt
local_llama_index.egg-info/dependency_links.txt
local_llama_index.egg-info/requires.txt
local_llama_index.egg-info/top_level.txt
local_llama_index/composability/__init__.py
local_llama_index/composability/base.py
local_llama_index/composability/joint_qa_summary.py
local_llama_index/data_structs/__init__.py
local_llama_index/data_structs/data_structs.py
local_llama_index/data_structs/data_structs_v2.py
local_llama_index/data_structs/node_v2.py
local_llama_index/data_structs/struct_type.py
local_llama_index/data_structs/table.py
local_llama_index/data_structs/table_v2.py
local_llama_index/embeddings/__init__.py
local_llama_index/embeddings/base.py
local_llama_index/embeddings/langchain.py
local_llama_index/embeddings/openai.py
local_llama_index/embeddings/utils.py
local_llama_index/evaluation/__init__.py
local_llama_index/evaluation/base.py
local_llama_index/indices/__init__.py
local_llama_index/indices/base.py
local_llama_index/indices/prompt_helper.py
local_llama_index/indices/registry.py
local_llama_index/indices/service_context.py
local_llama_index/indices/utils.py
local_llama_index/indices/common/__init__.py
local_llama_index/indices/common/struct_store/__init__.py
local_llama_index/indices/common/struct_store/base.py
local_llama_index/indices/common/struct_store/schema.py
local_llama_index/indices/common/struct_store/sql.py
local_llama_index/indices/common_tree/__init__.py
local_llama_index/indices/common_tree/base.py
local_llama_index/indices/composability/__init__.py
local_llama_index/indices/composability/graph.py
local_llama_index/indices/empty/__init__.py
local_llama_index/indices/empty/base.py
local_llama_index/indices/empty/query.py
local_llama_index/indices/keyword_table/__init__.py
