Metadata-Version: 2.1
Name: local-llama-index
Version: 0.5.11
Summary: Interface between LLMs and your data.
Home-page: https://github.com/jerryjliu/gpt_index
License: MIT
Platform: UNKNOWN
